{
  "title": "Fairhope mayor, council spar on governmental powers on professional services - Gulf Coast Media",
  "description": "While the Fairhope City Council passed a resolution last week that authorized spending $9,730 for a mountain bike trail feasibility study at the Triangle Property, it led to a disagreement over  &hellip;",
  "url": "https://gulfcoastmedia.com/the-courier/stories/fairhope-mayor-council-spar-on-governmental-powers-on-professional-services,73884",
  "image": "https://beta.creativecirclecdn.com/gulfcoast/original/1470163322_577e.jpg",
  "charset": "UTF-8"
}